RobustCrawl/__init__.py
RobustCrawl/context_pool.py
RobustCrawl/counter.py
RobustCrawl/exceptions.py
RobustCrawl/page_func.py
RobustCrawl/proxy_manager.py
RobustCrawl/request_pool.py
RobustCrawl/singleton_meta.py
RobustCrawl/token_bucket.py
RobustCrawl/proxy_protocol/__init__.py
RobustCrawl/proxy_protocol/hysteria.py
RobustCrawl/proxy_protocol/shadowsocks.py
RobustCrawl/proxy_protocol/trojan.py
RobustCrawl/proxy_protocol/v2ray.py
RobustCrawl-0.1.dist-info/LICENSE
RobustCrawl-0.1.dist-info/METADATA
RobustCrawl-0.1.dist-info/WHEEL
RobustCrawl-0.1.dist-info/top_level.txt
RobustCrawl-0.1.dist-info/RECORD
