Metadata-Version: 2.1
Name: RobustCrawl
Version: 0.1
Summary: A library for robust cralwer based on proxy pool and token bucket, support browser and requests
Home-page: https://github.com/R0k1e/RobustCrawl.git
Author: Haoyu Wang
Author-email: Haoyu_Wang_1103@outlook.com
Classifier: Programming Language :: Python :: 3
Classifier: License :: OSI Approved :: MIT License
Classifier: Operating System :: OS Independent
Requires-Python: >=3.11
License-File: LICENSE
Requires-Dist: gevent
Requires-Dist: playwright
Requires-Dist: tenacity
Requires-Dist: brotil
Requires-Dist: numpy
Requires-Dist: requests
Requires-Dist: pyyaml
Requires-Dist: bs4
Requires-Dist: fake-useragent
Requires-Dist: openai
